netbox_branching/__init__.py
netbox_branching/choices.py
netbox_branching/constants.py
netbox_branching/contextvars.py
netbox_branching/database.py
netbox_branching/events.py
netbox_branching/filtersets.py
netbox_branching/jobs.py
netbox_branching/middleware.py
netbox_branching/navigation.py
netbox_branching/search.py
netbox_branching/signal_receivers.py
netbox_branching/signals.py
netbox_branching/template_content.py
netbox_branching/urls.py
netbox_branching/utilities.py
netbox_branching/views.py
netbox_branching/webhook_callbacks.py
netbox_branching/api/__init__.py
netbox_branching/api/serializers.py
netbox_branching/api/urls.py
netbox_branching/api/views.py
netbox_branching/forms/__init__.py
netbox_branching/forms/bulk_edit.py
netbox_branching/forms/bulk_import.py
netbox_branching/forms/filtersets.py
netbox_branching/forms/misc.py
netbox_branching/forms/model_forms.py
netbox_branching/merge_strategies/__init__.py
netbox_branching/merge_strategies/iterative.py
netbox_branching/merge_strategies/squash.py
netbox_branching/merge_strategies/strategy.py
netbox_branching/migrations/0001_initial.py
netbox_branching/migrations/0002_branch_schema_id_unique.py
netbox_branching/migrations/0003_rename_indexes.py
netbox_branching/migrations/0004_copy_migrations.py
netbox_branching/migrations/0005_branch_applied_migrations.py
netbox_branching/migrations/0006_tag_object_types.py
netbox_branching/migrations/0007_branch_merge_strategy.py
netbox_branching/migrations/__init__.py
netbox_branching/models/__init__.py
netbox_branching/models/branches.py
netbox_branching/models/changes.py
netbox_branching/tables/__init__.py
netbox_branching/tables/columns.py
netbox_branching/tables/tables.py
netbox_branching/templates/netbox_branching/branch.html
netbox_branching/templates/netbox_branching/branch_action.html
netbox_branching/templates/netbox_branching/branch_archive.html
netbox_branching/templates/netbox_branching/branch_migrate.html
netboxlabs_netbox_branching-0.8.1.dist-info/licenses/LICENSE.md
netboxlabs_netbox_branching-0.8.1.dist-info/METADATA
netboxlabs_netbox_branching-0.8.1.dist-info/WHEEL
netboxlabs_netbox_branching-0.8.1.dist-info/top_level.txt
netboxlabs_netbox_branching-0.8.1.dist-info/RECORD
